{"inkVersion":20,"root":[[{"->":"Start"},["done",{"#f":5,"#n":"g-0"}],null],"done",{"Start":[["ev","str","^work","/str","/ev",{"VAR=":"problem_type","re":true},"ev","str","^Hello there","/str","/ev",{"*":".^.c-0","flg":20},{"c-0":["^ ",{"->":"Problem"},"\n",{"#f":5}]}],{"#f":1}],"Problem":[["ev",{"VAR?":"guest_name"},"out","/ev","^: Quick, I need one boba tea!","\n","ev","str","^What's the hurry?","/str","/ev",{"*":".^.c-0","flg":20},{"c-0":["^ ",{"->":"conv1"},"\n",{"#f":5}]}],{"#f":1}],"conv1":[["ev",{"VAR?":"guest_name"},"out","/ev","^: You remember the boy I met, right? We went on a not realy date-date. And it went... wrong.","\n","ev","str","^Huh?","/str","/ev",{"*":".^.c-0","flg":20},{"c-0":["^ ",{"->":"conv2"},"\n",{"#f":5}]}],{"#f":1}],"conv2":[["ev",{"VAR?":"guest_name"},"out","/ev","^: We were talking about art and suddenly we are at the local museum grabbing a painting and running off. A really expensive one.","\n","ev","str","^Oh god! Need help putting it back?","/str","/ev",{"*":".^.c-0","flg":20},{"c-0":["\n",{"->":"conv4"},{"#f":5}]}],{"#f":1}],"conv4":[["ev",{"VAR?":"guest_name"},"out","/ev","^: Hell no! It's ours now! Symbolises our relationship.","\n","ev","str","^Move in together and hang it on the wall.","/str","/ev",{"*":".^.c-0","flg":20},"ev","str","^I think you should put it back.","/str","/ev",{"*":".^.c-1","flg":20},"ev","str","^Sell it on the black market!","/str","/ev",{"*":".^.c-2","flg":20},"ev","str","^I can make you the owner of that artwork!","/str","/ev",{"*":".^.c-3","flg":20},{"c-0":["^ ",{"->":"Bad"},"\n",{"#f":5}],"c-1":[{"->":"Good"},"\n",{"#f":5}],"c-2":["^ ",{"->":"Ignore"},"\n",{"#f":5}],"c-3":["^ ",{"->":"Epic"},"\n",{"#f":5}]}],{"#f":1}],"Good":[["ev",{"VAR?":"guest_name"},"out","/ev","^:   I don't wanna! But I guess I should...","\n","ev","str","^It's gonna be okay.","/str","/ev",{"*":".^.c-0","flg":20},{"c-0":["\n","ev",true,"/ev",{"VAR=":"adviced","re":true},{"->":"Boba"},{"#f":5}]}],{"#f":1}],"Bad":[["ev",{"VAR?":"guest_name"},"out","/ev","^:  Oh my, that would be great!","\n","ev","str","^I am happy for you two!","/str","/ev",{"*":".^.c-0","flg":20},{"c-0":["\n","ev",true,"/ev",{"VAR=":"adviced","re":true},{"->":"Boba"},{"#f":5}]}],{"#f":1}],"Epic":[["ev",{"VAR?":"guest_name"},"out","/ev","^:  Thank you, thank you, thank you!","\n","ev","str","^Haha, neat-o.","/str","/ev",{"*":".^.c-0","flg":20},{"c-0":["\n","ev",true,"/ev",{"VAR=":"adviced","re":true},"ev",{"VAR?":"epic_used"},1,"+",{"VAR=":"epic_used","re":true},"/ev",{"->":"Boba"},{"#f":5}]}],{"#f":1}],"Ignore":["ev",{"VAR?":"guest_name"},"out","/ev","^: ... What are you thinking?!","\n","ev",{"VAR?":"friendship"},1,"-",{"VAR=":"friendship","re":true},"/ev",{"->":"Boba"},{"#f":1}],"Boba":[["ev",{"VAR?":"char_name"},"out","/ev","^: Sooo, what do you need today?","\n","ev",{"VAR?":"adviced"},"_","/ev",[{"->":".^.b","c":true},{"b":["\n","ev",{"VAR?":"guest_name"},"out","/ev","^: I like the taste of ","ev",{"VAR?":"fav_taste"},"out","/ev","^.","\n",{"->":"Boba.0.11"},null]}],"nop","\n",["ev",{"^->":"Boba.0.13.$r1"},{"temp=":"$r"},"str",{"->":".^.s"},[{"#n":"$r1"}],"/str","/ev",{"*":".^.^.c-0","flg":18},{"s":["^OPEN BOBATEA SCREEN",{"->":"$r","var":true},null]}],{"c-0":["ev",{"^->":"Boba.0.c-0.$r2"},"/ev",{"temp=":"$r"},{"->":".^.^.13.s"},[{"#n":"$r2"}],"\n","ev",true,"/ev",{"VAR=":"bobatea_open","re":true},"ev",{"VAR?":"char_name"},"out","/ev","^: Did you like it?","\n","ev",{"VAR?":"bobatea_success"},"/ev",["du","ev",5,"==","/ev",{"->":".^.b","c":true},{"b":["pop","\n","ev",{"VAR?":"guest_name"},"out","/ev","^: It's surprisingly good! I'm amazed!","\n","ev",{"VAR?":"char_name"},"out","/ev","^: Oh, thank you very much!","\n","ev",{"VAR?":"days_out"},1,"-",{"VAR=":"days_out","re":true},"/ev",{"->":".^.^.^.27"},null]}],["du","ev",4,"==","/ev",{"->":".^.b","c":true},{"b":["pop","\n","ev",{"VAR?":"guest_name"},"out","/ev","^: It was quite good! One thing wasn't perfect though: I didn' t like th ","ev",{"VAR?":"bad_choice"},"out","/ev","^ in the drink.","\n","ev",{"VAR?":"char_name"},"out","/ev","^: Thank you, next time I'll know!!","\n",{"->":".^.^.^.27"},null]}],["du","ev",3,"==","/ev",{"->":".^.b","c":true},{"b":["pop","\n","ev",{"VAR?":"guest_name"},"out","/ev","^: ... it was... fine. Really.","\n","ev",{"VAR?":"char_name"},"out","/ev","^: Oh, thank you very much!","\n","ev",{"VAR?":"friendship"},"_",{"VAR?":"friendship_breakpoint"},">","/ev",[{"->":".^.b","c":true},{"b":["\n","ev",{"VAR?":"guest_name"},"out","/ev","^: But you should know that I didn't like the choice for ","ev",{"VAR?":"bad_choice"},"out","/ev","^.","\n","ev",{"VAR?":"char_name"},"out","/ev","^: Oh, thank you very much! I try to remember that!","\n",{"->":".^.^.^.21"},null]}],"nop","\n",{"->":".^.^.^.27"},null]}],["du","ev",2,"==","/ev",{"->":".^.b","c":true},{"b":["pop","\n","ev",{"VAR?":"guest_name"},"out","/ev","^: It was... not good.","\n","ev",{"VAR?":"char_name"},"out","/ev","^: I'm sorry.","\n","ev",{"VAR?":"friendship"},"_",{"VAR?":"friendship_breakpoint"},"<","/ev",[{"->":".^.b","c":true},{"b":["\n","ev",{"VAR?":"days_out"},1,"+",{"VAR=":"days_out","re":true},"/ev",{"->":".^.^.^.21"},null]}],"nop","\n",{"->":".^.^.^.27"},null]}],["du","ev",1,"==","/ev",{"->":".^.b","c":true},{"b":["pop","\n","ev",{"VAR?":"guest_name"},"out","/ev","^: It is very bad. You only did YX good.","\n","ev",{"VAR?":"char_name"},"out","/ev","^: Oh, thank you very much!","\n","ev",{"VAR?":"friendship"},"_",{"VAR?":"friendship_breakpoint"},"<","/ev",[{"->":".^.b","c":true},{"b":["\n","ev",{"VAR?":"days_out"},1,"+",{"VAR=":"days_out","re":true},"/ev",{"->":".^.^.^.21"},null]}],"nop","\n",{"->":".^.^.^.27"},null]}],["du","ev",0,"==","/ev",{"->":".^.b","c":true},{"b":["pop","\n","ev",{"VAR?":"guest_name"},"out","/ev","^: Distrous. I don't think I'll come back soon!","\n","ev",{"VAR?":"char_name"},"out","/ev","^: Sorry... very sorry.","\n","ev",{"VAR?":"friendship"},"_",{"VAR?":"friendship_breakpoint"},"<","/ev",[{"->":".^.b","c":true},{"b":["\n","ev",{"VAR?":"days_out"},2,"+",{"VAR=":"days_out","re":true},"/ev",{"->":".^.^.^.21"},null]}],"nop","\n",{"->":".^.^.^.27"},null]}],"pop","nop","\n",{"->":"Bye"},{"#f":5}]}],{"#f":1}],"Bye":["ev",{"VAR?":"guest_name"},"out","/ev","^: Okay, bye.","\n","ev",{"VAR?":"char_name"},"out","/ev","^: Bye bye.","\n","end",{"#f":1}],"global decl":["ev",0,{"VAR=":"boba_Tea"},"str","^Angel","/str",{"VAR=":"char_name"},0,{"VAR=":"epic_used"},false,{"VAR=":"bobatea_open"},1,{"VAR=":"day"},"str","^rainy","/str",{"VAR=":"weather"},"str","^Mira","/str",{"VAR=":"guest_name"},"str","^negative","/str",{"VAR=":"guest_type"},"str","^lime","/str",{"VAR=":"fav_taste"},"str","^x","/str",{"VAR=":"fav_bubble"},0,{"VAR=":"friendship"},2,{"VAR=":"friendship_breakpoint"},1,{"VAR=":"days_out"},"str","^romance","/str",{"VAR=":"problem_type"},4,{"VAR=":"problem_lvl"},false,{"VAR=":"adviced"},2,{"VAR=":"bobatea_success"},"str","^milk","/str",{"VAR=":"bad_choice"},"str","^milk","/str",{"VAR=":"good_choice"},"str","^Epic","/str",{"VAR=":"prev_lvl_choice"},"str","^none","/str",{"VAR=":"this_lvl_choice"},"/ev","end",null],"#f":1}],"listDefs":{}}